fusion_engine_client/__init__.py
fusion_engine_client/analysis/__init__.py
fusion_engine_client/analysis/analyzer.py
fusion_engine_client/analysis/attitude.py
fusion_engine_client/analysis/data_loader.py
fusion_engine_client/applications/__init__.py
fusion_engine_client/applications/import_utils.py
fusion_engine_client/applications/p1_capture.py
fusion_engine_client/applications/p1_display.py
fusion_engine_client/applications/p1_extract.py
fusion_engine_client/applications/p1_filter.py
fusion_engine_client/applications/p1_lband_extract.py
fusion_engine_client/applications/p1_print.py
fusion_engine_client/messages/__init__.py
fusion_engine_client/messages/configuration.py
fusion_engine_client/messages/control.py
fusion_engine_client/messages/core.py
fusion_engine_client/messages/defs.py
fusion_engine_client/messages/device.py
fusion_engine_client/messages/fault_control.py
fusion_engine_client/messages/gnss_corrections.py
fusion_engine_client/messages/measurement_details.py
fusion_engine_client/messages/measurements.py
fusion_engine_client/messages/ros.py
fusion_engine_client/messages/signal_def_gen.py
fusion_engine_client/messages/signal_defs.py
fusion_engine_client/messages/solution.py
fusion_engine_client/messages/sta5635.py
fusion_engine_client/messages/timestamp.py
fusion_engine_client/parsers/__init__.py
fusion_engine_client/parsers/decoder.py
fusion_engine_client/parsers/encoder.py
fusion_engine_client/parsers/fast_indexer.py
fusion_engine_client/parsers/file_index.py
fusion_engine_client/parsers/mixed_log_reader.py
fusion_engine_client/utils/__init__.py
fusion_engine_client/utils/argument_parser.py
fusion_engine_client/utils/bin_utils.py
fusion_engine_client/utils/construct_utils.py
fusion_engine_client/utils/enum_utils.py
fusion_engine_client/utils/log.py
fusion_engine_client/utils/numpy_utils.py
fusion_engine_client/utils/print_utils.py
fusion_engine_client/utils/socket_timestamping.py
fusion_engine_client/utils/time_range.py
fusion_engine_client-1.25.0.dist-info/METADATA
fusion_engine_client-1.25.0.dist-info/WHEEL
fusion_engine_client-1.25.0.dist-info/entry_points.txt
fusion_engine_client-1.25.0.dist-info/top_level.txt
fusion_engine_client-1.25.0.dist-info/RECORD
