Metadata-Version: 2.4
Name: fusion-engine-client
Version: 1.25.0
Summary: Point One FusionEngine Library
Home-page: https://github.com/PointOneNav/fusion-engine-client
Download-URL: https://github.com/PointOneNav/fusion-engine-client/archive/refs/tags/v1.25.0.tar.gz
Author: Point One Navigation
Author-email: support@pointonenav.com
License: MIT
Classifier: Development Status :: 5 - Production/Stable
Classifier: Intended Audience :: Developers
Classifier: Intended Audience :: End Users/Desktop
Classifier: Intended Audience :: Science/Research
Classifier: License :: OSI Approved :: MIT License
Classifier: Operating System :: MacOS :: MacOS X
Classifier: Operating System :: Microsoft :: Windows
Classifier: Operating System :: POSIX
Classifier: Programming Language :: Python
Classifier: Programming Language :: Python :: 3
Classifier: Programming Language :: Python :: 3.6
Classifier: Programming Language :: Python :: 3.7
Classifier: Programming Language :: Python :: 3.8
Classifier: Programming Language :: Python :: 3.9
Classifier: Programming Language :: Python :: 3.10
Classifier: Programming Language :: Python :: 3.11
Classifier: Topic :: Software Development :: Libraries
Classifier: Topic :: Software Development :: Libraries :: Python Modules
Requires-Python: >=3.6
Requires-Dist: palettable>=3.3.0
Requires-Dist: argparse-formatter>=1.4
Requires-Dist: colorama>=0.4.4
Requires-Dist: scipy>=1.5.0
Requires-Dist: construct>=2.10.0
Requires-Dist: numpy>=1.16.0
Requires-Dist: p1-gpstime>=0.6.3.dev1
Requires-Dist: aenum>=3.1.1
Requires-Dist: packaging>=21.0.0
Requires-Dist: pymap3d>=2.4.3
Requires-Dist: plotly>=4.0.0
Provides-Extra: all
Provides-Extra: dev
Provides-Extra: display
Provides-Extra: tools
Dynamic: author
Dynamic: author-email
Dynamic: classifier
Dynamic: description
Dynamic: description-content-type
Dynamic: download-url
Dynamic: home-page
Dynamic: license
Dynamic: provides-extra
Dynamic: requires-dist
Dynamic: requires-python
Dynamic: summary
